vigilant_sdk/__init__.py
vigilant_sdk/alerts.py
vigilant_sdk/attributes.py
vigilant_sdk/batcher.py
vigilant_sdk/config.py
vigilant_sdk/instance.py
vigilant_sdk/logs.py
vigilant_sdk/message.py
vigilant_sdk/passthrough.py
vigilant_sdk/router.py
vigilant_sdk/types.py
vigilant_sdk/utils.py
vigilant_sdk/vigilant.py
vigilant_sdk/integrations/__init__.py
vigilant_sdk/integrations/fastapi.py
vigilant_sdk-1.0.0.dist-info/METADATA
vigilant_sdk-1.0.0.dist-info/WHEEL
vigilant_sdk-1.0.0.dist-info/top_level.txt
vigilant_sdk-1.0.0.dist-info/RECORD
