Metadata-Version: 2.4
Name: vigilant-sdk
Version: 1.0.0
Summary: Python SDK for Vigilant (https://vigilant.run)
Home-page: https://vigilant.run
Author: Vigilant Team
Author-email: Vigilant Team <support@vigilant.run>
Project-URL: Homepage, https://vigilant.run
Requires-Python: >=3.7
Requires-Dist: requests>=2.28.0
Provides-Extra: fastapi
Requires-Dist: fastapi>=0.68.0; extra == "fastapi"
Dynamic: author
Dynamic: home-page
Dynamic: requires-python
